tui_delta/__init__.py
tui_delta/__main__.py
tui_delta/_version.py
tui_delta/clear_lines.py
tui_delta/clear_rules.py
tui_delta/cli.py
tui_delta/consolidate_clears.py
tui_delta/escape_decoder.py
tui_delta/run.py
tui_delta/tui_profiles.yaml
tui_delta-0.2.0.dist-info/METADATA
tui_delta-0.2.0.dist-info/WHEEL
tui_delta-0.2.0.dist-info/entry_points.txt
tui_delta-0.2.0.dist-info/licenses/LICENSE
tui_delta-0.2.0.dist-info/RECORD
