Metadata-Version: 2.4
Name: tui_delta
Version: 0.2.0
Summary: Run a TUI application (AI assistant sessions, et al) with real-time delta processing for monitoring and logging. Supports Claude Code.
Project-URL: Homepage, https://github.com/JeffreyUrban/tui-delta
Project-URL: Repository, https://github.com/JeffreyUrban/tui-delta
Project-URL: Issues, https://github.com/JeffreyUrban/tui-delta/issues
Author: Jeffrey Urban
License: MIT License
License-File: LICENSE
Keywords: terminal
Classifier: Development Status :: 4 - Beta
Classifier: Environment :: Console
Classifier: Intended Audience :: Developers
Classifier: Intended Audience :: System Administrators
Classifier: License :: OSI Approved :: MIT License
Classifier: Operating System :: OS Independent
Classifier: Programming Language :: Python :: 3
Classifier: Programming Language :: Python :: 3.9
Classifier: Programming Language :: Python :: 3.10
Classifier: Programming Language :: Python :: 3.11
Classifier: Programming Language :: Python :: 3.12
Classifier: Programming Language :: Python :: 3.13
Classifier: Programming Language :: Python :: 3.14
Classifier: Topic :: System :: Logging
Classifier: Topic :: Terminals
Classifier: Topic :: Text Processing :: Filters
Classifier: Topic :: Utilities
Requires-Python: >=3.9
Requires-Dist: patterndb-yaml>=0.1.0
Requires-Dist: rich>=13.0.0
Requires-Dist: typer>=0.9.0
Requires-Dist: uniqseq>=0.1.0
Provides-Extra: dev
Requires-Dist: pre-commit>=3.6.0; extra == 'dev'
Requires-Dist: pyright>=1.1.0; extra == 'dev'
Requires-Dist: pytest-cov>=4.1.0; extra == 'dev'
Requires-Dist: pytest>=7.4.0; extra == 'dev'
Requires-Dist: ruff>=0.1.9; extra == 'dev'
Provides-Extra: docs
Requires-Dist: mkdocs-material>=9.5.0; extra == 'docs'
Requires-Dist: mkdocstrings[python]>=0.25.0; extra == 'docs'
Requires-Dist: pymdown-extensions>=10.0.0; extra == 'docs'
Requires-Dist: sybil>=6.0.0; extra == 'docs'
Requires-Dist: termynal>=0.12.0; extra == 'docs'
